part3/verilog/handshake.v

// ready: !o_empty from sfp_row 


module handshake(reset, clk, ready, ack, req);

input reset;
input clk;
input ready;
input ack;
output req;


parameter SIZE = 2;

parameter IDLE = 2'b00; 
parameter READY = 2'b01; // pause for a few cycle for preparing data
parameter SENT_WAIT = 2'b10;

reg [1:0] counter;


reg   [SIZE-1:0]    state;  // current state
wire  [SIZE-1:0]    next_state   ;


assign next_state = fsm_function(state, ready, ack, counter);

assign req = (state == SENT_WAIT);

function [SIZE-1:0] fsm_function;
    input [SIZE-1:0] state;
    input ready;
    input ack;
    input [1:0] counter;
    case (state)
     IDLE: if (ready) begin
                fsm_function = READY;
            end else 
                fsm_function = IDLE;
     READY: if (counter == 2'b11) begin  
                fsm_function = SENT_WAIT;
            end else
                fsm_function = READY;
     SENT_WAIT: if (ack) begin
                fsm_function = IDLE;
            end else 
                fsm_function = SENT_WAIT;
     default : fsm_function = IDLE;
    endcase
endfunction



always @ (posedge clk)
    begin
    if (reset) begin
        state <=  IDLE;
        counter <= 0;
    end else begin
        state <=  next_state;
        if (state == READY) begin
            counter <= counter + 1;
        end else begin
            counter <= 0;
        end
    end
end

endmodule

part3/verilog/handshake_tb.v
module handshake_tb;


reg reset;
reg clk;
reg ready;
reg ack;
wire req;


handshake handshake_init (
    .reset(reset), 
    .clk(clk), 
    .ready(ready), 
    .ack(ack), 
    .req(req)
);


initial begin 

  $dumpfile("handshake_tb.vcd");
  $dumpvars(0,handshake_tb);

  #0.5 clk = 1'b0;
  reset = 1;  ready = 0; ack = 0;
  #0.5 clk = 1'b1;

  #0.5 clk = 1'b0; // idle
  reset = 0;  
  #0.5 clk = 1'b1;

  #0.5 clk = 1'b0;
  ready = 1;
  #0.5 clk = 1'b1;

  #0.5 clk = 1'b0; // READY
  #0.5 clk = 1'b1;

    #0.5 clk = 1'b0;
    #0.5 clk = 1'b1;

    #0.5 clk = 1'b0;
    #0.5 clk = 1'b1;

    #0.5 clk = 1'b0; // ns: SENT_WAIT , counter == 1'b11, req = 1;
    #0.5 clk = 1'b1;

    #0.5 clk = 1'b0; // SENT_WAIT , counter == 1'b00, 
    #0.5 clk = 1'b1;

    #0.5 clk = 1'b0;
    ack = 1;
    #0.5 clk = 1'b1;

    #0.5 clk = 1'b0;
    #0.5 clk = 1'b1;
end

endmodule

part3/handshake_tb.vcd
$date
	Tue Mar 15 16:53:46 2022
$end
$version
	Icarus Verilog
$end
$timescale
	1s
$end
$scope module handshake_tb $end
$var wire 1 ! req $end
$var reg 1 " ack $end
$var reg 1 # clk $end
$var reg 1 $ ready $end
$var reg 1 % reset $end
$scope module handshake_init $end
$var wire 1 " ack $end
$var wire 1 # clk $end
$var wire 1 $ ready $end
$var wire 1 % reset $end
$var wire 1 ! req $end
$var wire 2 & next_state [1:0] $end
$var reg 2 ' counter [1:0] $end
$var reg 2 ( state [1:0] $end
$scope function fsm_function $end
$var reg 1 ) ack $end
$var reg 2 * counter [1:0] $end
$var reg 2 + fsm_function [1:0] $end
$var reg 1 , ready $end
$var reg 2 - state [1:0] $end
$upscope $end
$upscope $end
$upscope $end
$enddefinitions $end
#0
$dumpvars
bx -
x,
b0 +
bx *
x)
bx (
bx '
b0 &
x%
x$
x#
x"
x!
$end
#1
0)
0,
0"
0$
1%
0#
#2
b0 *
b0 -
b0 '
0!
b0 (
1#
#3
0%
0#
#4
1#
#5
b1 &
b1 +
1,
1$
0#
#6
b1 -
b1 (
1#
#7
0#
#8
b1 *
b1 '
1#
#9
0#
#10
b10 *
b10 '
1#
#11
0#
#12
b10 &
b10 +
b11 *
b11 '
1#
#13
0#
#14
b0 *
b10 -
b0 '
1!
b10 (
1#
#15
0#
#16
1#
#17
b0 &
b0 +
1)
1"
0#
#18
b1 &
b1 +
b0 -
0!
b0 (
1#
#19
0#
#20
b1 -
b1 (
1#
